adria/__init__.py
adria/core/__init__.py
adria/core/generator.py
adria/core/utils.py
adria/project.py
adria-0.1.0.dist-info/LICENSE
adria-0.1.0.dist-info/METADATA
adria-0.1.0.dist-info/WHEEL
adria-0.1.0.dist-info/RECORD
