Metadata-Version: 2.1
Name: adria
Version: 0.1.0
Summary: Programmer-friendly Static Site Generator
License: MIT
Keywords: static,site,generator
Author: Šarūnas Navickas
Author-email: sarunas@griaustinis.lt
Requires-Python: >=3.11,<4.0
Classifier: License :: OSI Approved :: MIT License
Classifier: Programming Language :: Python :: 3
Classifier: Programming Language :: Python :: 3.11
Requires-Dist: jinja2 (>=3.1.2,<4.0.0)
Requires-Dist: pydantic (>=1.10.8,<2.0.0)
